{"0": "affirm", "1": "bot_challenge", "2": "chitchat", "3": "cyber_security_complaint_1", "4": "cyber_security_complaint_4", "5": "deny", "6": "goodbye", "7": "greet", "8": "keep_anonymous", "9": "mood_great", "10": "mood_unhappy", "11": "out_of_scope", "12": "provide_employee_id", "13": "sexual_harassment_complaint_3", "14": "sexual_harassment_complaint_new", "15": "tell_date_and_time", "16": "tell_dept", "17": "tell_name", "18": "tell_violater_name", "19": "thanks", "20": "violater_name_not_known"}